{
  "type": "immersiveengineering:sawmill",
  "secondaries": [
    {
      "output": {
        "tag": "forge:dusts/wood"
      },
      "stripping": true
    },
    {
      "output": {
        "tag": "forge:dusts/wood"
      },
      "stripping": false
    }
  ],
  "result": {
    "item": "quark:azalea_planks",
    "count": 6
  },
  "energy": 1600,
  "input": [
    {
      "item": "quark:azalea_log"
    },
    {
      "item": "quark:azalea_wood"
    }
  ],
  "stripped": {
    "item": "quark:stripped_azalea_log"
  }
}